LICENSE
treefrog/__init__.py
treefrog/__main__.py
treefrog/cli.py
treefrog/flatten/__main__.py
treefrog/organize/__init__.py
treefrog/organize/__main__.py
treefrog/parse/__init__.py
treefrog/parse/parsers.py
treefrog/parse/utils.py
treefrog/rename/__init__.py
treefrog/rename/__main__.py
treefrog/tree.py
treefrog-0.7.1.dist-info/entry_points.txt
treefrog-0.7.1.dist-info/LICENSE
treefrog-0.7.1.dist-info/WHEEL
treefrog-0.7.1.dist-info/METADATA
treefrog-0.7.1.dist-info/RECORD
