Metadata-Version: 2.1
Name: treefrog
Version: 0.7.1
Summary: Organize the Slippi game files in your filesystem according to their attributes
Home-page: https://github.com/dawsonbooth/treefrog
License: MIT
Keywords: filesystem,slp,slippi,slippi-replays
Author: Dawson Booth
Author-email: pypi@dawsonbooth.com
Requires-Python: >=3.8,<4.0
Classifier: Environment :: Console
Classifier: License :: OSI Approved :: MIT License
Classifier: Operating System :: OS Independent
Classifier: Programming Language :: Python :: 3
Classifier: Programming Language :: Python :: 3.8
Classifier: Programming Language :: Python :: 3.9
Requires-Dist: py-slippi (>=1.6.1,<2.0.0)
Requires-Dist: tqdm (>=4.56.2,<5.0.0)
Project-URL: Documentation, https://dawsonbooth.github.io/treefrog
Project-URL: Repository, https://github.com/dawsonbooth/treefrog
